arenasdk/__init__.py
arenasdk/client/__init__.py
arenasdk/client/client.py
arenasdk/client/node_client.py
arenasdk/client/serving_client.py
arenasdk/client/training_client.py
arenasdk/common/__init__.py
arenasdk/common/log.py
arenasdk/common/util.py
arenasdk/enums/__init__.py
arenasdk/enums/types.py
arenasdk/exceptions/__init__.py
arenasdk/exceptions/arena_exception.py
arenasdk/fields/__init__.py
arenasdk/fields/fields.py
arenasdk/logger/__init__.py
arenasdk/logger/logger.py
arenasdk/nodes/__init__.py
arenasdk/nodes/gpu_exclusive_node.py
arenasdk/nodes/gpu_topology_node.py
arenasdk/nodes/gpushare_node.py
arenasdk/nodes/node.py
arenasdk/nodes/node_set.py
arenasdk/nodes/normal_node.py
arenasdk/serving/__init__.py
arenasdk/serving/custom_job_builder.py
arenasdk/serving/job.py
arenasdk/serving/job_builder.py
arenasdk/serving/kf_job_builder.py
arenasdk/serving/serving_job_info.py
arenasdk/serving/tensorflow_job_builder.py
arenasdk/serving/tensorrt_job_builder.py
arenasdk/training/__init__.py
arenasdk/training/et_job_builder.py
arenasdk/training/horovod_job_builder.py
arenasdk/training/job.py
arenasdk/training/job_builder.py
arenasdk/training/mpi_job_builder.py
arenasdk/training/pytorch_job_builder.py
arenasdk/training/scalein_etjob_builder.py
arenasdk/training/scaleout_etjob_builder.py
arenasdk/training/spark_job_builder.py
arenasdk/training/tensorflow_job_builder.py
arenasdk/training/training_job_info.py
arenasdk/training/volcano_job_builder.py
arenasdk-0.10.0.dist-info/LICENSE
arenasdk-0.10.0.dist-info/METADATA
arenasdk-0.10.0.dist-info/WHEEL
arenasdk-0.10.0.dist-info/top_level.txt
arenasdk-0.10.0.dist-info/RECORD
