Metadata-Version: 2.1
Name: arenasdk
Version: 0.10.0
Summary: Python SDK For Arena
Home-page: https://arena-docs.readthedocs.io/en/latest
Author: AlanFok
Author-email: huozhixin2868@163.com
License: UNKNOWN
Platform: UNKNOWN
License-File: LICENSE
Requires-Dist: pyyaml
Requires-Dist: coloredlogs
